WebSocketClient/__init__.py
WebSocketClient/keywords.py
WebSocketClient/version.py
robotframework_websocketclient-1.3.0.dist-info/top_level.txt
robotframework_websocketclient-1.3.0.dist-info/METADATA
robotframework_websocketclient-1.3.0.dist-info/DESCRIPTION.rst
robotframework_websocketclient-1.3.0.dist-info/metadata.json
robotframework_websocketclient-1.3.0.dist-info/WHEEL
robotframework_websocketclient-1.3.0.dist-info/RECORD
