Metadata-Version: 2.0
Name: robotframework-websocketclient
Version: 1.3.0
Summary: Robot Framework keywords for websocket-client
Home-page: https://github.com/greums/robotframework-websocketclient
Author: Damien Le Bourdonnec
Author-email: greumsworkshop@gmail.com
License: MIT
Download-URL: https://github.com/greums/robotframework-websocketclient/tarball/1.3.0
Keywords: robotframework,websocket
Platform: any
Classifier: Development Status :: 5 - Production/Stable
Classifier: Framework :: Robot Framework :: Library
Classifier: License :: OSI Approved :: MIT License
Classifier: Programming Language :: Python :: 2.7
Classifier: Programming Language :: Python :: 3
Classifier: Programming Language :: Python :: 3.3
Classifier: Programming Language :: Python :: 3.4
Classifier: Programming Language :: Python :: 3.5
Classifier: Programming Language :: Python :: 3.6
Classifier: Topic :: Software Development :: Testing
Requires-Dist: robotframework
Requires-Dist: websocket-client
